{
  "members": [
    {
      "id": 1,
      "avatar_url": "https://images.unsplash.com/photo-1546447147-3fc2b8181a74?ixlib=rb-1.2.1&ixid=eyJhcHBfaWQiOjEyMDd9&auto=format&fit=crop&w=500&q=60",
      "name": "Vick da Silva",
      "email": "vick@cao.auau",
      "birth": 954806400000,
      "gender": "F",
      "blood": "AB",
      "weight": "80",
      "height": "50"
    },
    {
      "id": 2,
      "avatar_url": "https://images.unsplash.com/photo-1543852786-1cf6624b9987?ixlib=rb-1.2.1&ixid=eyJhcHBfaWQiOjEyMDd9&auto=format&fit=crop&w=500&q=60",
      "name": "bily",
      "email": "bili@bilinha",
      "birth": 1286668800000,
      "gender": "F",
      "blood": "O",
      "weight": "70",
      "height": "50"
    }
  ],
  "instructors": [
    {
      "id": 3,
      "name": "Professora Solange",
      "avatar_url": "https://images.unsplash.com/photo-1518617840859-acd542e13a99?ixlib=rb-1.2.1&ixid=eyJhcHBfaWQiOjEyMDd9&auto=format&fit=crop&w=500&q=60",
      "birth": 1591228800000,
      "gender": "F",
      "services": "só senta",
      "created_at": 1590867442960
    },
    {
      "id": 4,
      "name": "Maria",
      "avatar_url": "https://images.unsplash.com/photo-1468112014733-deb9e1f8ddd2?ixlib=rb-1.2.1&ixid=eyJhcHBfaWQiOjEyMDd9&auto=format&fit=crop&w=500&q=60",
      "birth": 718070400000,
      "gender": "F",
      "services": "surf",
      "created_at": 1591220984882
    }
  ]
}
